apigateway_sqs_lambda/__init__.py
apigateway_sqs_lambda/py.typed
apigateway_sqs_lambda/_jsii/__init__.py
apigateway_sqs_lambda/_jsii/apigateway-sqs-lambda@0.0.5.jsii.tgz
apigateway_sqs_lambda-0.0.5.dist-info/LICENSE
apigateway_sqs_lambda-0.0.5.dist-info/METADATA
apigateway_sqs_lambda-0.0.5.dist-info/WHEEL
apigateway_sqs_lambda-0.0.5.dist-info/top_level.txt
apigateway_sqs_lambda-0.0.5.dist-info/RECORD
