Metadata-Version: 2.1
Name: apigateway-sqs-lambda
Version: 0.0.5
Summary: Package provides opinionated constrcut for API Gateway with associated SQS queue and Lambda function
Home-page: https://github.com/FBosler/apigateway-sqs-lambda.git
Author: Fabian<FBosler@gmail.com>
License: Apache-2.0
Project-URL: Source, https://github.com/FBosler/apigateway-sqs-lambda.git
Classifier: Intended Audience :: Developers
Classifier: Operating System :: OS Independent
Classifier: Programming Language :: JavaScript
Classifier: Programming Language :: Python :: 3 :: Only
Classifier: Programming Language :: Python :: 3.7
Classifier: Programming Language :: Python :: 3.8
Classifier: Programming Language :: Python :: 3.9
Classifier: Programming Language :: Python :: 3.10
Classifier: Typing :: Typed
Classifier: Development Status :: 4 - Beta
Classifier: License :: OSI Approved
Requires-Python: ~=3.7
License-File: LICENSE
Requires-Dist: aws-cdk-lib (<3.0.0,>=2.1.0)
Requires-Dist: aws-solutions-constructs.core (==2.25.0)
Requires-Dist: constructs (<11.0.0,>=10.0.5)
Requires-Dist: jsii (<2.0.0,>=1.70.0)
Requires-Dist: publication (>=0.0.3)
Requires-Dist: typeguard (~=2.13.3)
